direx/__init__.py
direx/direx.py
dirEx-0.0.6.dist-info/LICENSE
dirEx-0.0.6.dist-info/METADATA
dirEx-0.0.6.dist-info/WHEEL
dirEx-0.0.6.dist-info/top_level.txt
dirEx-0.0.6.dist-info/RECORD
