Metadata-Version: 2.1
Name: dirEx
Version: 0.0.6
Summary: An extension to the built-in function dir()
Home-page: https://github.com/floydawong/dirEx.git
Author: Floyda
Author-email: floyda@163.com
License: MIT
Keywords: dir extend built-in
Platform: UNKNOWN
